feelpp_aptly_publisher/__init__.py
feelpp_aptly_publisher/__main__.py
feelpp_aptly_publisher/cli.py
feelpp_aptly_publisher/publisher.py
feelpp_aptly_publisher/py.typed
feelpp_aptly_publisher-1.2.1.dist-info/METADATA
feelpp_aptly_publisher-1.2.1.dist-info/WHEEL
feelpp_aptly_publisher-1.2.1.dist-info/entry_points.txt
feelpp_aptly_publisher-1.2.1.dist-info/top_level.txt
feelpp_aptly_publisher-1.2.1.dist-info/RECORD
