Metadata-Version: 2.4
Name: feelpp-aptly-publisher
Version: 1.2.1
Summary: Tool to publish Debian packages to Feel++ APT repository via aptly and GitHub Pages
Author-email: Christophe Prud'homme <christophe.prudhomme@cemosis.fr>
Maintainer-email: Christophe Prud'homme <christophe.prudhomme@cemosis.fr>
License: LGPL-3.0-or-later
Project-URL: Homepage, https://github.com/feelpp/apt
Project-URL: Documentation, https://github.com/feelpp/apt#readme
Project-URL: Repository, https://github.com/feelpp/apt.git
Project-URL: Issues, https://github.com/feelpp/apt/issues
Project-URL: Feel++ Main, https://docs.feelpp.org
Project-URL: APT Repository, https://feelpp.github.io/apt/
Keywords: apt,debian,packaging,aptly,github-pages,feelpp
Classifier: Development Status :: 4 - Beta
Classifier: Intended Audience :: Developers
Classifier: License :: OSI Approved :: GNU Lesser General Public License v3 or later (LGPLv3+)
Classifier: Operating System :: POSIX :: Linux
Classifier: Programming Language :: Python :: 3
Classifier: Programming Language :: Python :: 3.8
Classifier: Programming Language :: Python :: 3.9
Classifier: Programming Language :: Python :: 3.10
Classifier: Programming Language :: Python :: 3.11
Classifier: Programming Language :: Python :: 3.12
Classifier: Topic :: Software Development :: Build Tools
Classifier: Topic :: System :: Archiving :: Packaging
Requires-Python: >=3.8
Provides-Extra: dev
Requires-Dist: pytest>=7.0; extra == "dev"
Requires-Dist: pytest-cov>=4.0; extra == "dev"
Requires-Dist: black>=23.0; extra == "dev"
Requires-Dist: flake8>=6.0; extra == "dev"
Requires-Dist: flake8-bugbear>=23.0; extra == "dev"
Requires-Dist: flake8-comprehensions>=3.0; extra == "dev"
Requires-Dist: mypy>=1.0; extra == "dev"
Requires-Dist: build>=1.0; extra == "dev"
Requires-Dist: twine>=4.0; extra == "dev"
